dvg_devices/Aim_TTi_PSU_demo.py
dvg_devices/Aim_TTi_PSU_protocol_RS232.py
dvg_devices/Aim_TTi_PSU_qdev.py
dvg_devices/Arduino_protocol_serial.py
dvg_devices/BaseDevice.py
dvg_devices/Bronkhorst_MFC_demo.py
dvg_devices/Bronkhorst_MFC_protocol_RS232.py
dvg_devices/Bronkhorst_MFC_qdev.py
dvg_devices/Compax3_servo_demo.py
dvg_devices/Compax3_servo_protocol_RS232.py
dvg_devices/Compax3_servo_qdev.py
dvg_devices/Compax3_servo_step_navigator_GUI.py
dvg_devices/Julabo_circulator_demo.py
dvg_devices/Julabo_circulator_protocol_RS232.py
dvg_devices/Julabo_circulator_qdev.py
dvg_devices/Keysight_3497xA_demo.py
dvg_devices/Keysight_3497xA_demo_logger.py
dvg_devices/Keysight_3497xA_protocol_SCPI.py
dvg_devices/Keysight_3497xA_qdev.py
dvg_devices/Keysight_N8700_demo.py
dvg_devices/Keysight_N8700_protocol_SCPI.py
dvg_devices/Keysight_N8700_qdev.py
dvg_devices/MDrive_example_motion_program_x.mxt
dvg_devices/MDrive_example_motion_program_z.mxt
dvg_devices/MDrive_stepper_demo.py
dvg_devices/MDrive_stepper_protocol_RS422.py
dvg_devices/MDrive_stepper_qdev.py
dvg_devices/Picotech_PT104_demo.py
dvg_devices/Picotech_PT104_protocol_UDP.py
dvg_devices/Picotech_PT104_qdev.py
dvg_devices/PolyScience_PD_bath_protocol_RS232.py
dvg_devices/ThermoFlex_chiller_demo.py
dvg_devices/ThermoFlex_chiller_protocol_RS232.py
dvg_devices/ThermoFlex_chiller_qdev.py
dvg_devices/Traverse_layout.png
dvg_devices/XylemHydrovarHVL_CRC_tools.py
dvg_devices/XylemHydrovarHVL_demo.py
dvg_devices/XylemHydrovarHVL_protocol_RTU.py
dvg_devices/XylemHydrovarHVL_qdev.py
dvg_devices/_Qt_tests.py
dvg_devices/_init_.py
dvg_devices/config/port_Bronkhorst_MFC_1.txt
dvg_devices/config/port_MDrive.txt
dvg_devices-1.5.2.dist-info/AUTHORS.rst
dvg_devices-1.5.2.dist-info/LICENSE.txt
dvg_devices-1.5.2.dist-info/METADATA
dvg_devices-1.5.2.dist-info/WHEEL
dvg_devices-1.5.2.dist-info/top_level.txt
dvg_devices-1.5.2.dist-info/RECORD
