Metadata-Version: 2.1
Name: dvg-devices
Version: 1.5.2
Summary: Collection of I/O interfaces to communicate with microcontroller boards and laboratory devices, with optional PyQt/PySide multithread support and graphical user-interfaces.
Home-page: https://python-dvg-devices.readthedocs.io
Author: Dennis van Gils
Author-email: vangils.dennis@gmail.com
License: MIT
Project-URL: Issue Tracker, https://github.com/Dennis-van-Gils/python-dvg-devices/issues
Keywords: PyQt5,PyQt6,PySide2,PySide6,device I/O,automation,laboratory,science,control,experiment,multithread,Arduino,serial,VISA
Classifier: Development Status :: 5 - Production/Stable
Classifier: License :: OSI Approved :: MIT License
Classifier: Intended Audience :: Developers
Classifier: Intended Audience :: Science/Research
Classifier: Operating System :: OS Independent
Classifier: Programming Language :: Python
Classifier: Programming Language :: Python :: 3
Classifier: Topic :: Scientific/Engineering 
Classifier: Topic :: Scientific/Engineering :: Electronic Design Automation (EDA)
Classifier: Topic :: Scientific/Engineering :: Physics
Requires-Python: >=3.6
License-File: LICENSE.txt
License-File: AUTHORS.rst
Requires-Dist: dvg-debug-functions ~=2.5
Requires-Dist: dvg-pid-controller ~=2.2
Requires-Dist: dvg-pyqt-controls ~=1.5
Requires-Dist: dvg-pyqt-filelogger ~=1.4
Requires-Dist: dvg-pyqtgraph-threadsafe ~=3.4
Requires-Dist: dvg-qdeviceio ~=1.6
Requires-Dist: matplotlib ~=3.1
Requires-Dist: numpy <3.0,>=1.15
Requires-Dist: pyserial ~=3.4
Requires-Dist: pyvisa ~=1.11
Requires-Dist: qtpy
Provides-Extra: pyqt5
Requires-Dist: pyqt5 ~=5.12 ; extra == 'pyqt5'
Provides-Extra: pyqt6
Requires-Dist: pyqt6 ; extra == 'pyqt6'
Provides-Extra: pyside2
Requires-Dist: pyside2 ; extra == 'pyside2'
Provides-Extra: pyside6
Requires-Dist: pyside6 ; extra == 'pyside6'
